codebase_context/__init__.py
codebase_context/__main__.py
codebase_context/cli.py
codebase_context/config.py
codebase_context/core.py
codebase_context/filesystem.py
codebase_context/vcs.py
codebase_context-0.1.5.dist-info/licenses/LICENCE
codebase_context-0.1.5.dist-info/METADATA
codebase_context-0.1.5.dist-info/WHEEL
codebase_context-0.1.5.dist-info/entry_points.txt
codebase_context-0.1.5.dist-info/top_level.txt
codebase_context-0.1.5.dist-info/RECORD
