Metadata-Version: 2.4
Name: codebase-context
Version: 0.1.5
Author-email: Julian Kimmig <julian.kimmig@gmx.net>
License: MIT
Requires-Python: >=3.10
License-File: LICENCE
Requires-Dist: click>=8.1.8
Requires-Dist: gitpython>=3.1.44
Requires-Dist: wrapconfig[all]<0.3.0,>=0.2.2
Dynamic: license-file
